heap_mapping/__init__.py
heap_mapping/min_max_heap.py
heap_mapping-0.1.0.dist-info/licenses/LICENSE
heap_mapping-0.1.0.dist-info/METADATA
heap_mapping-0.1.0.dist-info/WHEEL
heap_mapping-0.1.0.dist-info/top_level.txt
heap_mapping-0.1.0.dist-info/RECORD
