Metadata-Version: 2.4
Name: heap-mapping
Version: 0.1.0
Summary: An implementation of a Min-Max Heap with a MutableMapping interface.
Author-email: Andrew Tapia <andrew.tapia@uky.edu>
Project-URL: Homepage, https://github.com/actapia/min-max-heap-mapping
Project-URL: Bug Tracker, https://github.com/actapia/min-max-heap-mapping
Classifier: Programming Language :: Python :: 3
Classifier: License :: OSI Approved :: MIT License
Classifier: Operating System :: OS Independent
Requires-Python: >=3.12
License-File: LICENSE
Dynamic: license-file
